[
  {
    "ticker": "ENS/USDT",
    "high": null,
    "low": 24.98,
    "close": 28.62
  },
  {
    "ticker": "INSP/USDT",
    "high": null,
    "low": 0.0397,
    "close": 0.05558
  },
  {
    "ticker": "SENATE/USDT",
    "high": null,
    "low": 0.04794,
    "close": 0.05346
  },
  {
    "ticker": "BEAMX/USDT",
    "high": null,
    "low": 0.01519,
    "close": 0.01607
  },
  {
    "ticker": "SFUND/USDT",
    "high": null,
    "low": 1.527,
    "close": 1.611
  },
  {
    "ticker": "LOOKS/USDT",
    "high": null,
    "low": 0.04756,
    "close": 0.05842
  },
  {
    "ticker": "THG/USDT",
    "high": null,
    "low": 0.03663,
    "close": 0.03845
  },
  {
    "ticker": "AURORA/USDT",
    "high": 0.1835,
    "low": null,
    "close": 0.1474
  },
  {
    "ticker": "ERN/USDT",
    "high": null,
    "low": 2.338,
    "close": 2.467
  },
  {
    "ticker": "KAS/USDT",
    "high": 0.1938,
    "low": null,
    "close": 0.17816
  },
  {
    "ticker": "RTF/USDT",
    "high": null,
    "low": 0.1405,
    "close": 0.14626
  },
  {
    "ticker": "NAKA/USDT",
    "high": null,
    "low": 0.9964,
    "close": 1.0413
  },
  {
    "ticker": "ANKR/USDT",
    "high": null,
    "low": 0.0292,
    "close": 0.0303
  },
  {
    "ticker": "PHB/USDT",
    "high": null,
    "low": 1.7118,
    "close": 1.7866
  },
  {
    "ticker": "HOT/USDT",
    "high": null,
    "low": 0.00166,
    "close": 0.001871
  }
]