[
  {
    "ticker": "ENS/USDT",
    "upTrend": false,
    "start_date": "2024-07-15T16:00:00",
    "extrems_date": "2024-07-18T04:00:00"
  },
  {
    "ticker": "INSP/USDT",
    "upTrend": false,
    "start_date": "2024-05-31T04:00:00",
    "extrems_date": "2024-06-14T12:00:00"
  },
  {
    "ticker": "SENATE/USDT",
    "upTrend": false,
    "start_date": "2024-06-16T08:00:00",
    "extrems_date": "2024-06-28T12:00:00"
  },
  {
    "ticker": "BEAMX/USDT",
    "upTrend": true,
    "start_date": "2024-07-04T20:00:00",
    "extrems_date": "2024-07-18T04:00:00"
  },
  {
    "ticker": "SFUND/USDT",
    "upTrend": false,
    "start_date": "2024-06-12T08:00:00",
    "extrems_date": "2024-06-28T16:00:00"
  },
  {
    "ticker": "LOOKS/USDT",
    "upTrend": false,
    "start_date": "2024-06-12T08:00:00",
    "extrems_date": "2024-06-17T20:00:00"
  },
  {
    "ticker": "THG/USDT",
    "upTrend": false,
    "start_date": "2024-06-23T04:00:00",
    "extrems_date": "2024-07-05T00:00:00"
  },
  {
    "ticker": "AURORA/USDT",
    "upTrend": true,
    "start_date": "2024-07-16T08:00:00",
    "extrems_date": "2024-07-17T00:00:00"
  },
  {
    "ticker": "ERN/USDT",
    "upTrend": false,
    "start_date": "2024-07-18T04:00:00",
    "extrems_date": "2024-07-18T08:00:00"
  },
  {
    "ticker": "KAS/USDT",
    "upTrend": false,
    "start_date": "2024-07-15T20:00:00",
    "extrems_date": "2024-07-16T04:00:00"
  },
  {
    "ticker": "RTF/USDT",
    "upTrend": false,
    "start_date": "2024-05-20T08:00:00",
    "extrems_date": "2024-06-05T12:00:00"
  },
  {
    "ticker": "NAKA/USDT",
    "upTrend": false,
    "start_date": "2024-07-15T16:00:00",
    "extrems_date": "2024-07-18T08:00:00"
  },
  {
    "ticker": "ANKR/USDT",
    "upTrend": false,
    "start_date": "2024-07-17T04:00:00",
    "extrems_date": "2024-07-18T08:00:00"
  },
  {
    "ticker": "PHB/USDT",
    "upTrend": false,
    "start_date": "2024-07-17T04:00:00",
    "extrems_date": "2024-07-18T08:00:00"
  },
  {
    "ticker": "HOT/USDT",
    "upTrend": false,
    "start_date": "2024-06-20T04:00:00",
    "extrems_date": "2024-07-04T20:00:00"
  }
]